<dialogue id="B20-A10-C2-1522940361401">
  <utterance participant="builder">
    <!--Mission has started .-->
    <markable id="markable_6" ambiguity="unambiguous" category="person" disagreement_type="no_disagreement" gender="unspecified" generic="generic-no" gram_fnc="unmarked" mark_type="phrase" min_ids="word_0" min_words="mission" mmax_level="phrase" number="undersp-num" order_id="6" person="per1" ref_type="phrase" reference="new" related_object="no" span="(0, 1)">
      <t>Mission</t>
    </markable>
    <t>has started .</t>
  </utterance>
  <utterance participant="builder">added green@-3,0,4 added green@-2,0,5; green@-2,1,5; green@-3,0,5 removed green@-2,1,5 removed green@-3,0,4 removed green@-2,0,5 removed green@-3,0,5<!--added green@-3,0,4 added green@-2,0,5; green@-2,1,5; green@-3,0,5 removed green@-2,1,5 removed green@-3,0,4 removed green@-2,0,5 removed green@-3,0,5-->
  </utterance>
  <utterance participant="architect">
    <!--so this one is a flaoting structure-->
    <t>so</t>
    <markable id="markable_107" gender="unmarked" gram_fnc="unmarked" mark_type="phrase" mmax_level="phrase" number="unmarked" person="unmarked" reference="unmarked" span="(11, 13)">
      <t>this one</t>
    </markable>
    <t>is</t>
    <markable id="markable_0" ambiguity="unambiguous" category="person" disagreement_type="no_disagreement" gender="unspecified" generic="generic-no" gram_fnc="unmarked" mark_type="phrase" mmax_level="phrase" number="undersp-num" order_id="0" person="per1" ref_type="phrase" reference="new" related_object="no" span="(14, 17)">
      <t>a flaoting structure</t>
    </markable>
  </utterance>
  <utterance participant="builder">.<!--.-->
  </utterance>
  <utterance participant="architect">
    <!--start with a square ( 2 by 2 ) in the center-->
    <t>start with</t>
    <markable id="markable_8" ambiguity="unambiguous" category="person" disagreement_type="no_disagreement" gender="unspecified" generic="generic-no" gram_fnc="unmarked" mark_type="phrase" min_ids="word_21" min_words="square" mmax_level="phrase" number="undersp-num" order_id="8" person="per1" ref_type="phrase" reference="new" related_object="no" span="(20, 26)">
      <t>a square ( 2 by 2</t>
    </markable>
    <t>) in</t>
    <markable id="markable_9" ambiguity="unambiguous" category="person" disagreement_type="no_disagreement" gender="unspecified" generic="generic-no" gram_fnc="unmarked" mark_type="phrase" min_ids="word_30" min_words="colour" mmax_level="phrase" number="undersp-num" order_id="9" person="per1" ref_type="phrase" reference="new" related_object="no" span="(28, 30)">
      <t>the center</t>
    </markable>
  </utterance>
  <utterance participant="builder">
    <!--colour ?-->
    <markable id="markable_108" gender="unmarked" gram_fnc="unmarked" mark_type="phrase" mmax_level="phrase" number="unmarked" person="unmarked" reference="unmarked" span="(30, 31)">
      <t>colour</t>
    </markable>
    <t>?</t>
  </utterance>
  <utterance participant="builder">added green@-1,0,0<!--added green@-1,0,0-->
  </utterance>
  <utterance participant="architect">
    <!--does n't matter , you 'll be removing them to get the structure to float-->
    <t>does n't matter ,</t>
    <markable id="markable_109" gender="unmarked" gram_fnc="unmarked" mark_type="phrase" mmax_level="phrase" number="unmarked" person="unmarked" reference="unmarked" span="(37, 38)">
      <t>you</t>
    </markable>
    <t>'ll be removing</t>
    <markable id="markable_3" ambiguity="unambiguous" category="person" disagreement_type="no_disagreement" gender="unspecified" generic="generic-no" gram_fnc="unmarked" mmax_level="phrase" number="undersp-num" order_id="3" person="per1" phrase_antecedent="single_phrase" ref_type="phrase" reference="old" related_object="no" span="(41, 42)">
      <t>them</t>
    </markable>
    <t>to get</t>
    <markable id="markable_11" ambiguity="unambiguous" category="person" disagreement_type="no_disagreement" gender="unspecified" generic="generic-no" gram_fnc="unmarked" min_ids="word_45" min_words="structure" mmax_level="phrase" number="undersp-num" order_id="11" person="per1" ref_type="phrase" reference="new" related_object="no" span="(44, 46)">
      <t>the structure</t>
    </markable>
    <t>to float</t>
  </utterance>
  <utterance participant="builder">added green@0,0,-1 added green@0,0,0 added green@-1,0,-1<!--added green@0,0,-1 added green@0,0,0 added green@-1,0,-1-->
  </utterance>
  <utterance participant="architect">
    <!--the structure contains red blocks attached only at the edges of the perimeter of the square you just put down-->
    <markable id="markable_12" ambiguity="unambiguous" category="person" disagreement_type="no_disagreement" gender="unspecified" generic="generic-no" gram_fnc="unmarked" min_ids="word_52" min_words="blocks" mmax_level="phrase" number="undersp-num" order_id="12" person="per1" ref_type="phrase" reference="new" related_object="no" span="(51, 53)">
      <t>the structure</t>
    </markable>
    <t>contains</t>
    <markable id="markable_110" gender="unmarked" gram_fnc="unmarked" mark_type="phrase" mmax_level="phrase" number="unmarked" person="unmarked" reference="unmarked" span="(54, 71)">
      <t>red blocks attached only at</t>
      <markable id="markable_13" ambiguity="unambiguous" category="person" disagreement_type="no_disagreement" gender="unspecified" generic="generic-no" gram_fnc="unmarked" mark_type="phrase" min_ids="word_60" min_words="edges" mmax_level="phrase" number="undersp-num" order_id="13" person="per1" ref_type="phrase" reference="new" related_object="no" span="(59, 71)">
        <t>the edges of</t>
        <markable id="markable_14" ambiguity="unambiguous" category="person" disagreement_type="no_disagreement" gender="unspecified" generic="generic-no" gram_fnc="unmarked" mark_type="phrase" min_ids="word_63" min_words="perimeter" mmax_level="phrase" number="undersp-num" order_id="14" person="per1" ref_type="phrase" reference="new" related_object="no" span="(62, 71)">
          <t>the perimeter of</t>
          <markable id="markable_15" ambiguity="unambiguous" category="person" disagreement_type="no_disagreement" gender="unspecified" generic="generic-no" gram_fnc="unmarked" mark_type="phrase" min_ids="word_66" min_words="square" mmax_level="phrase" number="undersp-num" order_id="15" person="per1" ref_type="phrase" reference="new" related_object="no" span="(65, 71)">
            <t>the square</t>
            <markable id="markable_16" ambiguity="unambiguous" category="person" disagreement_type="no_disagreement" gender="unspecified" generic="generic-no" gram_fnc="unmarked" mark_type="phrase" min_ids="word_67" min_words="you" mmax_level="phrase" number="undersp-num" order_id="16" person="per1" ref_type="phrase" reference="new" related_object="no" span="(67, 68)">
              <t>you</t>
            </markable>
            <t>just put down</t>
          </markable>
        </markable>
      </markable>
    </markable>
  </utterance>
  <utterance participant="builder">added red@-1,1,-1 added red@-2,1,-1 removed red@-1,1,-1 added red@-2,1,0 added red@-2,1,1 added red@-1,1,1 added red@0,1,1 added red@1,1,1 added red@-2,1,-2 added red@-1,1,-2 added red@0,1,-2 added red@1,1,-2 added red@1,0,-1 removed red@1,0,-1<!--added red@-1,1,-1 added red@-2,1,-1 removed red@-1,1,-1 added red@-2,1,0 added red@-2,1,1 added red@-1,1,1 added red@0,1,1 added red@1,1,1 added red@-2,1,-2 added red@-1,1,-2 added red@0,1,-2 added red@1,1,-2 added red@1,0,-1 removed red@1,0,-1-->
  </utterance>
  <utterance participant="architect">
    <!--that is right !-->
    <markable id="markable_111" gender="unmarked" gram_fnc="unmarked" mark_type="phrase" mmax_level="phrase" number="unmarked" person="unmarked" reference="unmarked" span="(85, 86)">
      <t>that</t>
    </markable>
    <t>is right !</t>
  </utterance>
  <utterance participant="architect">
    <!--just remove the corners-->
    <t>just remove</t>
    <markable id="markable_112" gender="unmarked" gram_fnc="unmarked" mark_type="phrase" mmax_level="phrase" number="unmarked" person="unmarked" reference="unmarked" span="(91, 93)">
      <t>the corners</t>
    </markable>
  </utterance>
  <utterance participant="builder">added red@1,1,-1 added red@1,1,0 removed red@1,1,1 removed red@-2,1,1 removed red@-2,1,-2 removed red@1,1,-2 removed red@-2,1,0 added red@-2,1,0<!--added red@1,1,-1 added red@1,1,0 removed red@1,1,1 removed red@-2,1,1 removed red@-2,1,-2 removed red@1,1,-2 removed red@-2,1,0 added red@-2,1,0-->
  </utterance>
  <utterance participant="architect">cool<!--cool-->
  </utterance>
  <utterance participant="builder">removed green@0,0,0 removed green@0,0,-1 removed green@-1,0,-1 removed green@-1,0,0<!--removed green@0,0,0 removed green@0,0,-1 removed green@-1,0,-1 removed green@-1,0,0-->
  </utterance>
  <utterance participant="builder">alrighty<!--alrighty-->
  </utterance>
  <utterance participant="architect">
    <!--the next layer up is similar in that you 're building on the perimeter with purple blocks-->
    <markable id="markable_20" ambiguity="unambiguous" category="person" disagreement_type="no_disagreement" gender="unspecified" generic="generic-no" gram_fnc="unmarked" mark_type="phrase" min_ids="word_108" min_words="perimeter" mmax_level="phrase" number="undersp-num" order_id="20" person="per1" ref_type="phrase" reference="new" related_object="no" span="(107, 111)">
      <t>the next layer up</t>
    </markable>
    <t>is similar in that</t>
    <markable id="markable_23" ambiguity="unambiguous" category="person" disagreement_type="no_disagreement" gender="unspecified" generic="generic-no" gram_fnc="unmarked" mark_type="phrase" min_ids="word_115" min_words="difference" mmax_level="phrase" number="undersp-num" order_id="23" person="per1" ref_type="phrase" reference="new" related_object="no" span="(115, 116)">
      <t>you</t>
    </markable>
    <t>'re building on</t>
    <markable id="markable_113" gender="unmarked" gram_fnc="unmarked" mark_type="phrase" mmax_level="phrase" number="unmarked" person="unmarked" reference="unmarked" span="(119, 121)">
      <t>the perimeter</t>
    </markable>
    <t>with</t>
    <markable id="markable_24" ambiguity="unambiguous" category="person" disagreement_type="no_disagreement" gender="unspecified" generic="generic-no" gram_fnc="unmarked" mark_type="phrase" min_ids="word_124" min_words="perimeter" mmax_level="phrase" number="undersp-num" order_id="24" person="per1" ref_type="phrase" reference="new" related_object="no" span="(122, 124)">
      <t>purple blocks</t>
    </markable>
  </utterance>
  <utterance participant="builder">
    <!--what 's the difference ?-->
    <markable id="markable_114" gender="unmarked" gram_fnc="unmarked" mark_type="phrase" mmax_level="phrase" number="unmarked" person="unmarked" reference="unmarked" span="(124, 125)">
      <t>what</t>
    </markable>
    <t>'s</t>
    <markable id="markable_115" gender="unmarked" gram_fnc="unmarked" mark_type="phrase" mmax_level="phrase" number="unmarked" person="unmarked" reference="unmarked" span="(126, 128)">
      <t>the difference</t>
    </markable>
    <t>?</t>
  </utterance>
  <utterance participant="architect">
    <!--so follow the perimeter of the red on the edges with purple blocks .-->
    <t>so follow</t>
    <markable id="markable_116" gender="unmarked" gram_fnc="unmarked" mark_type="phrase" mmax_level="phrase" number="unmarked" person="unmarked" reference="unmarked" span="(131, 136)">
      <t>the perimeter of</t>
      <markable id="markable_25" ambiguity="unambiguous" category="person" disagreement_type="no_disagreement" gender="unspecified" generic="generic-no" gram_fnc="unmarked" mark_type="phrase" min_ids="word_135" min_words="edges" mmax_level="phrase" number="undersp-num" order_id="25" person="per1" ref_type="phrase" reference="new" related_object="no" span="(134, 136)">
        <t>the red</t>
      </markable>
    </markable>
    <t>on</t>
    <markable id="markable_117" gender="unmarked" gram_fnc="unmarked" mark_type="phrase" mmax_level="phrase" number="unmarked" person="unmarked" reference="unmarked" span="(137, 139)">
      <t>the edges</t>
    </markable>
    <t>with</t>
    <markable id="markable_26" ambiguity="unambiguous" category="person" disagreement_type="no_disagreement" gender="unspecified" generic="generic-no" gram_fnc="unmarked" mark_type="phrase" min_ids="word_141" min_words="blocks" mmax_level="phrase" number="undersp-num" order_id="26" person="per1" ref_type="phrase" reference="new" related_object="no" span="(140, 142)">
      <t>purple blocks</t>
    </markable>
    <t>.</t>
  </utterance>
  <utterance participant="architect">
    <!--The overall shape will be different is the main thing-->
    <markable id="markable_27" ambiguity="unambiguous" category="person" disagreement_type="no_disagreement" gender="unspecified" generic="generic-no" gram_fnc="unmarked" mark_type="phrase" min_ids="word_145" min_words="shape" mmax_level="phrase" number="undersp-num" order_id="27" person="per1" ref_type="phrase" reference="new" related_object="no" span="(143, 146)">
      <t>The overall shape</t>
    </markable>
    <t>will be different is</t>
    <markable id="markable_28" ambiguity="unambiguous" category="person" disagreement_type="no_disagreement" gender="unspecified" generic="generic-no" gram_fnc="unmarked" mark_type="phrase" min_ids="word_152" min_words="thing" mmax_level="phrase" number="undersp-num" order_id="28" person="per1" ref_type="phrase" reference="new" related_object="no" span="(150, 153)">
      <t>the main thing</t>
    </markable>
  </utterance>
  <utterance participant="builder">. added purple@-2,2,-1 added purple@-2,2,0 removed purple@-2,2,0 removed purple@-2,2,-1 added purple@-3,1,-1 added purple@-3,1,0 added purple@-2,1,1 added purple@-1,1,2<!--. added purple@-2,2,-1 added purple@-2,2,0 removed purple@-2,2,0 removed purple@-2,2,-1 added purple@-3,1,-1 added purple@-3,1,0 added purple@-2,1,1 added purple@-1,1,2-->
  </utterance>
  <utterance participant="architect">yes but one layer up<!--yes but one layer up-->
  </utterance>
  <utterance participant="builder">added purple@0,1,2 added purple@1,1,1 added purple@1,2,1 removed purple@1,1,1 added purple@1,2,2 removed purple@0,1,2 removed purple@-1,1,2 added purple@0,2,2 added purple@-1,2,2 removed purple@-2,1,1 removed purple@-3,1,0 removed purple@-3,1,-1 added purple@-2,2,2 added purple@-2,3,1; purple@-2,2,1 removed purple@-2,3,1 added purple@-3,2,1 added purple@-3,2,0 added purple@-3,2,-1 added purple@-3,2,-2 added purple@-2,2,-2 added purple@-2,2,-3 added purple@-1,2,-3 added purple@0,2,-3 added purple@1,2,-3 added purple@1,2,-2 added purple@2,2,-2 added purple@2,2,-1 added purple@2,2,0 removed purple@-3,2,1 removed purple@2,2,-2<!--added purple@0,1,2 added purple@1,1,1 added purple@1,2,1 removed purple@1,1,1 added purple@1,2,2 removed purple@0,1,2 removed purple@-1,1,2 added purple@0,2,2 added purple@-1,2,2 removed purple@-2,1,1 removed purple@-3,1,0 removed purple@-3,1,-1 added purple@-2,2,2 added purple@-2,3,1; purple@-2,2,1 removed purple@-2,3,1 added purple@-3,2,1 added purple@-3,2,0 added purple@-3,2,-1 added purple@-3,2,-2 added purple@-2,2,-2 added purple@-2,2,-3 added purple@-1,2,-3 added purple@0,2,-3 added purple@1,2,-3 added purple@1,2,-2 added purple@2,2,-2 added purple@2,2,-1 added purple@2,2,0 removed purple@-3,2,1 removed purple@2,2,-2-->
  </utterance>
  <utterance participant="architect">
    <!--very close . you just need to remove the blocks that are connected to the red only at the corners-->
    <t>very close .</t>
    <markable id="markable_118" gender="unmarked" gram_fnc="unmarked" mark_type="phrase" mmax_level="phrase" number="unmarked" person="unmarked" reference="unmarked" span="(200, 201)">
      <t>you</t>
    </markable>
    <t>just need to remove</t>
    <markable id="markable_119" gender="unmarked" gram_fnc="unmarked" mark_type="phrase" mmax_level="phrase" number="unmarked" person="unmarked" reference="unmarked" span="(205, 217)">
      <t>the blocks that are connected to</t>
      <markable id="markable_120" gender="unmarked" gram_fnc="unmarked" mark_type="phrase" mmax_level="phrase" number="unmarked" person="unmarked" reference="unmarked" span="(211, 213)">
        <t>the red</t>
      </markable>
      <t>only at</t>
      <markable id="markable_121" gender="unmarked" gram_fnc="unmarked" mark_type="phrase" mmax_level="phrase" number="unmarked" person="unmarked" reference="unmarked" span="(215, 217)">
        <t>the corners</t>
      </markable>
    </markable>
  </utterance>
  <utterance participant="builder">removed purple@1,2,-2 removed purple@1,2,1 removed purple@-2,2,1<!--removed purple@1,2,-2 removed purple@1,2,1 removed purple@-2,2,1-->
  </utterance>
  <utterance participant="architect">sorry<!--sorry-->
  </utterance>
  <utterance participant="builder">removed purple@-2,2,-2 removed purple@-2,2,-3 removed purple@-3,2,-2 removed purple@-2,2,2 removed purple@1,2,2 removed purple@1,2,-3<!--removed purple@-2,2,-2 removed purple@-2,2,-3 removed purple@-3,2,-2 removed purple@-2,2,2 removed purple@1,2,2 removed purple@1,2,-3-->
  </utterance>
  <utterance participant="builder">
    <!--wait this or something else ?-->
    <t>wait</t>
    <markable id="markable_124" gender="unmarked" gram_fnc="unmarked" mark_type="phrase" mmax_level="phrase" number="unmarked" person="unmarked" reference="unmarked" span="(228, 232)">
      <markable id="markable_122" gender="unmarked" gram_fnc="unmarked" mark_type="phrase" mmax_level="phrase" number="unmarked" person="unmarked" reference="unmarked" span="(228, 229)">
        <t>this</t>
      </markable>
      <t>or</t>
      <markable id="markable_123" gender="unmarked" gram_fnc="unmarked" mark_type="phrase" mmax_level="phrase" number="unmarked" person="unmarked" reference="unmarked" span="(230, 232)">
        <t>something else</t>
      </markable>
    </markable>
    <t>?</t>
  </utterance>
  <utterance participant="architect">
    <!--put back the purples at the left and right of each chunk . so like one left and up of you now-->
    <t>put back</t>
    <markable id="markable_125" gender="unmarked" gram_fnc="unmarked" mark_type="phrase" mmax_level="phrase" number="unmarked" person="unmarked" reference="unmarked" span="(235, 245)">
      <t>the purples at</t>
      <markable id="markable_126" gender="unmarked" gram_fnc="unmarked" mark_type="phrase" mmax_level="phrase" number="unmarked" person="unmarked" reference="unmarked" span="(238, 245)">
        <markable id="markable_127" gender="unmarked" gram_fnc="unmarked" mark_type="phrase" mmax_level="phrase" number="unmarked" person="unmarked" reference="unmarked" span="(238, 240)">
          <t>the left</t>
        </markable>
        <t>and</t>
        <markable id="markable_128" gender="unmarked" gram_fnc="unmarked" mark_type="phrase" mmax_level="phrase" number="unmarked" person="unmarked" reference="unmarked" span="(241, 242)">
          <t>right</t>
        </markable>
        <t>of</t>
        <markable id="markable_129" gender="unmarked" gram_fnc="unmarked" mark_type="phrase" mmax_level="phrase" number="unmarked" person="unmarked" reference="unmarked" span="(243, 245)">
          <t>each chunk</t>
        </markable>
      </markable>
    </markable>
    <t>. so like</t>
    <markable id="markable_38" ambiguity="unambiguous" category="person" disagreement_type="no_disagreement" gender="unspecified" generic="generic-no" gram_fnc="unmarked" min_ids="word_248" min_words="it" mmax_level="phrase" number="undersp-num" order_id="38" person="per1" ref_type="phrase" reference="new" related_object="no" span="(248, 249)">
      <t>one</t>
    </markable>
    <t>left and up of</t>
    <markable id="markable_130" gender="unmarked" gram_fnc="unmarked" mark_type="phrase" mmax_level="phrase" number="unmarked" person="unmarked" reference="unmarked" span="(253, 254)">
      <t>you</t>
    </markable>
    <t>now</t>
  </utterance>
  <utterance participant="builder">added purple@2,2,-2 added purple@1,2,-3 added purple@-3,2,-2<!--added purple@2,2,-2 added purple@1,2,-3 added purple@-3,2,-2-->
  </utterance>
  <utterance participant="architect">no<!--no-->
  </utterance>
  <utterance participant="builder">added purple@-2,2,-3 removed purple@-2,2,-3 removed purple@-3,2,-2 removed purple@2,2,-2 removed purple@1,2,-3 added purple@1,2,-1 added purple@1,2,-2 removed purple@1,2,-1<!--added purple@-2,2,-3 removed purple@-2,2,-3 removed purple@-3,2,-2 removed purple@2,2,-2 removed purple@1,2,-3 added purple@1,2,-1 added purple@1,2,-2 removed purple@1,2,-1-->
  </utterance>
  <utterance participant="builder">
    <!--this ?-->
    <markable id="markable_131" gender="unmarked" gram_fnc="unmarked" mark_type="phrase" mmax_level="phrase" number="unmarked" person="unmarked" reference="unmarked" span="(267, 268)">
      <t>this</t>
    </markable>
    <t>?</t>
  </utterance>
  <utterance participant="architect">yes<!--yes-->
  </utterance>
  <utterance participant="builder">added purple@-2,2,-1 added purple@-2,2,-2 removed purple@-2,2,-1 added purple@-1,2,1 added purple@-2,2,1 removed purple@-1,2,1 added purple@0,2,1 added purple@1,2,1; purple@1,3,1 removed purple@0,2,1 removed purple@1,3,1<!--added purple@-2,2,-1 added purple@-2,2,-2 removed purple@-2,2,-1 added purple@-1,2,1 added purple@-2,2,1 removed purple@-1,2,1 added purple@0,2,1 added purple@1,2,1; purple@1,3,1 removed purple@0,2,1 removed purple@1,3,1-->
  </utterance>
  <utterance participant="architect">
    <!--okay awesome sorry about that . this is is-->
    <t>okay awesome sorry about</t>
    <markable id="markable_132" gender="unmarked" gram_fnc="unmarked" mark_type="phrase" mmax_level="phrase" number="unmarked" person="unmarked" reference="unmarked" span="(284, 285)">
      <t>that</t>
    </markable>
    <t>.</t>
    <markable id="markable_133" gender="unmarked" gram_fnc="unmarked" mark_type="phrase" mmax_level="phrase" number="unmarked" person="unmarked" reference="unmarked" span="(286, 287)">
      <t>this</t>
    </markable>
    <t>is is</t>
  </utterance>
  <utterance participant="architect">it *<!--it *-->
  </utterance>
  <utterance participant="builder">cool<!--cool-->
  </utterance>
</dialogue>